[
  {
    "_id": {
      "$oid": "9a93c32dae927a326c65e847"
    },
    "type": "idea_subscribed",
    "fkId": {
      "$oid": "b6682b2b055d14a9b50da683"
    },
    "userId": {
      "$oid": "53241fad407ef95937248331"
    },
    "isSeen": true,
    "createdAt": {
      "$date": "2026-02-21T14:29:33.928Z"
    }
  },
  {
    "_id": {
      "$oid": "bba53758ed85851211512454"
    },
    "type": "idea_upvoted",
    "fkId": {
      "$oid": "0dacb314f7cc1b2b55571df5"
    },
    "userId": {
      "$oid": "f546ff3e8b00451f67c3724d"
    },
    "isSeen": false,
    "createdAt": {
      "$date": "2026-02-21T14:39:01.543Z"
    }
  },
  {
    "_id": {
      "$oid": "a55fa642c48e643a029ad60a"
    },
    "type": "challenge_upvoted",
    "fkId": {
      "$oid": "e23f198a75ef2c16121215f4"
    },
    "userId": {
      "$oid": "e995c32f1437cd735b64e3f3"
    },
    "isSeen": true,
    "createdAt": {
      "$date": "2026-02-21T14:29:31.499Z"
    }
  },
  {
    "_id": {
      "$oid": "3b7059ec18e3f24f5916358e"
    },
    "type": "challenge_deleted",
    "fkId": {
      "$oid": "8d78a2e96e74fc43fbe97a07"
    },
    "userId": {
      "$oid": "2bc621e1361d668aaabfbf57"
    },
    "isSeen": true,
    "createdAt": {
      "$date": "2026-02-21T14:34:49.965Z"
    }
  },
  {
    "_id": {
      "$oid": "d3c1557239efd8e6e81d4b91"
    },
    "type": "idea_upvoted",
    "fkId": {
      "$oid": "38d33015ec821d8b806a9f18"
    },
    "userId": {
      "$oid": "2b30fcf2e90897f2225edca8"
    },
    "isSeen": false,
    "createdAt": {
      "$date": "2026-02-21T14:36:01.949Z"
    }
  },
  {
    "_id": {
      "$oid": "02424467706ad1d715a03997"
    },
    "type": "idea_edited",
    "fkId": {
      "$oid": "05a72d8d66451cec8e8664f5"
    },
    "userId": {
      "$oid": "53241fad407ef95937248331"
    },
    "isSeen": false,
    "createdAt": {
      "$date": "2026-02-21T14:31:53.774Z"
    }
  },
  {
    "_id": {
      "$oid": "dc3e27ed4a41e74c5c20854e"
    },
    "type": "challenge_upvoted",
    "fkId": {
      "$oid": "e3234ecc4465911d52b3470b"
    },
    "userId": {
      "$oid": "18453cdfc20c9d7e345da6bb"
    },
    "isSeen": true,
    "createdAt": {
      "$date": "2026-02-21T14:30:52.391Z"
    }
  },
  {
    "_id": {
      "$oid": "26d177213a5ab0b744779a5e"
    },
    "type": "challenge_edited",
    "fkId": {
      "$oid": "8ecb24f2256ca9a4e18cc173"
    },
    "userId": {
      "$oid": "2bc621e1361d668aaabfbf57"
    },
    "isSeen": true,
    "createdAt": {
      "$date": "2026-02-21T14:37:51.823Z"
    }
  },
  {
    "_id": {
      "$oid": "0fe98b32dbc12bdec48b60da"
    },
    "type": "idea_edited",
    "fkId": {
      "$oid": "130d6c1ff33cafaa14129159"
    },
    "userId": {
      "$oid": "2bc621e1361d668aaabfbf57"
    },
    "isSeen": false,
    "createdAt": {
      "$date": "2026-02-21T14:23:38.468Z"
    }
  },
  {
    "_id": {
      "$oid": "91b0e65096105e9209f2b930"
    },
    "type": "idea_edited",
    "fkId": {
      "$oid": "75b9127d73404b70ce0098b2"
    },
    "userId": {
      "$oid": "7266fc2a6ba991e5e9f1a626"
    },
    "isSeen": false,
    "createdAt": {
      "$date": "2026-02-21T14:38:49.297Z"
    }
  },
  {
    "_id": {
      "$oid": "6e293cd421889d86b13a42f2"
    },
    "type": "idea_edited",
    "fkId": {
      "$oid": "130d6c1ff33cafaa14129159"
    },
    "userId": {
      "$oid": "f546ff3e8b00451f67c3724d"
    },
    "isSeen": true,
    "createdAt": {
      "$date": "2026-02-21T14:34:15.657Z"
    }
  },
  {
    "_id": {
      "$oid": "400a003c2ccca285c227b3e1"
    },
    "type": "idea_deleted",
    "fkId": {
      "$oid": "0082a9e9d0e59ef0ee1452d3"
    },
    "userId": {
      "$oid": "18453cdfc20c9d7e345da6bb"
    },
    "isSeen": true,
    "createdAt": {
      "$date": "2026-02-21T14:26:08.454Z"
    }
  },
  {
    "_id": {
      "$oid": "eefe1d6faf6b2e16cd8b6382"
    },
    "type": "idea_edited",
    "fkId": {
      "$oid": "93da01dba89e41b89b6faf04"
    },
    "userId": {
      "$oid": "b67695827cecb99d4ead1707"
    },
    "isSeen": true,
    "createdAt": {
      "$date": "2026-02-21T14:35:45.981Z"
    }
  },
  {
    "_id": {
      "$oid": "b8a572c96ada5989f14d5d48"
    },
    "type": "challenge_edited",
    "fkId": {
      "$oid": "50b527bafd61a0811d42e330"
    },
    "userId": {
      "$oid": "2e69c5f1d36087afbd354bca"
    },
    "isSeen": false,
    "createdAt": {
      "$date": "2026-02-21T14:37:26.401Z"
    }
  },
  {
    "_id": {
      "$oid": "679d742473f37b03b19f2332"
    },
    "type": "challenge_status_update",
    "fkId": {
      "$oid": "cc850c4b34b597d340d86fe8"
    },
    "userId": {
      "$oid": "268b8a5741b7bd1797a14026"
    },
    "isSeen": false,
    "createdAt": {
      "$date": "2026-02-21T14:29:54.955Z"
    }
  },
  {
    "_id": {
      "$oid": "c8d60e4660053b014f59fdd6"
    },
    "type": "challenge_commented",
    "fkId": {
      "$oid": "ae05fb1ab580ff7d24604d70"
    },
    "userId": {
      "$oid": "2e69c5f1d36087afbd354bca"
    },
    "isSeen": true,
    "createdAt": {
      "$date": "2026-02-21T14:38:47.076Z"
    }
  },
  {
    "_id": {
      "$oid": "af6e4caba712cb90daa57c3b"
    },
    "type": "challenge_edited",
    "fkId": {
      "$oid": "130d6c1ff33cafaa14129159"
    },
    "userId": {
      "$oid": "18453cdfc20c9d7e345da6bb"
    },
    "isSeen": false,
    "createdAt": {
      "$date": "2026-02-21T14:39:19.460Z"
    }
  },
  {
    "_id": {
      "$oid": "1db4d737b2b426e150baae45"
    },
    "type": "idea_subscribed",
    "fkId": {
      "$oid": "8581922593d0741f5a3c2245"
    },
    "userId": {
      "$oid": "6e9b6e972adf98037fb1eb13"
    },
    "isSeen": true,
    "createdAt": {
      "$date": "2026-02-21T14:26:01.800Z"
    }
  },
  {
    "_id": {
      "$oid": "cb2a40bfbfdfcd086eadb386"
    },
    "type": "idea_upvoted",
    "fkId": {
      "$oid": "13f18538201ea153031e6fb1"
    },
    "userId": {
      "$oid": "308297a4c754ce1f5200ce85"
    },
    "isSeen": false,
    "createdAt": {
      "$date": "2026-02-21T14:35:13.945Z"
    }
  },
  {
    "_id": {
      "$oid": "d4fd210de24cab54f57b6e6c"
    },
    "type": "challenge_upvoted",
    "fkId": {
      "$oid": "0082a9e9d0e59ef0ee1452d3"
    },
    "userId": {
      "$oid": "424aa1cdf5c40c8421367aa5"
    },
    "isSeen": false,
    "createdAt": {
      "$date": "2026-02-21T14:38:06.233Z"
    }
  },
  {
    "_id": {
      "$oid": "f2b8850bb6107b7519d6d056"
    },
    "type": "challenge_edited",
    "fkId": {
      "$oid": "fc901a55559e1699bbfb4528"
    },
    "userId": {
      "$oid": "2b30fcf2e90897f2225edca8"
    },
    "isSeen": false,
    "createdAt": {
      "$date": "2026-02-21T14:36:57.655Z"
    }
  },
  {
    "_id": {
      "$oid": "d155c382657b77cf121486f1"
    },
    "type": "challenge_upvoted",
    "fkId": {
      "$oid": "13d6591f3c1f6d9be45924b3"
    },
    "userId": {
      "$oid": "969bf9a0094364a075abab0b"
    },
    "isSeen": true,
    "createdAt": {
      "$date": "2026-02-21T14:29:49.979Z"
    }
  },
  {
    "_id": {
      "$oid": "ec223885254c68d20d5029cb"
    },
    "type": "idea_commented",
    "fkId": {
      "$oid": "380dc2e2df7ff60dac511033"
    },
    "userId": {
      "$oid": "e5ad220c675a802b9d2993ef"
    },
    "isSeen": false,
    "createdAt": {
      "$date": "2026-02-21T14:31:28.723Z"
    }
  },
  {
    "_id": {
      "$oid": "d9253f13f57b589b4de92b71"
    },
    "type": "idea_deleted",
    "fkId": {
      "$oid": "0c7a068970afeceb3d85f5b5"
    },
    "userId": {
      "$oid": "bef7a718d953662eebedbc13"
    },
    "isSeen": false,
    "createdAt": {
      "$date": "2026-02-21T14:25:44.563Z"
    }
  },
  {
    "_id": {
      "$oid": "5bfff09fa90105b78d6cb46e"
    },
    "type": "challenge_deleted",
    "fkId": {
      "$oid": "7babf239de2cde6789ecf39f"
    },
    "userId": {
      "$oid": "7266fc2a6ba991e5e9f1a626"
    },
    "isSeen": false,
    "createdAt": {
      "$date": "2026-02-21T14:31:26.450Z"
    }
  },
  {
    "_id": {
      "$oid": "7a8cbd3e62225231503e0d44"
    },
    "type": "challenge_commented",
    "fkId": {
      "$oid": "ab5609be28d75724d4f46af3"
    },
    "userId": {
      "$oid": "969bf9a0094364a075abab0b"
    },
    "isSeen": false,
    "createdAt": {
      "$date": "2026-02-21T14:23:58.538Z"
    }
  },
  {
    "_id": {
      "$oid": "622ba899c91226d600d6e29e"
    },
    "type": "challenge_upvoted",
    "fkId": {
      "$oid": "50b527bafd61a0811d42e330"
    },
    "userId": {
      "$oid": "b67695827cecb99d4ead1707"
    },
    "isSeen": true,
    "createdAt": {
      "$date": "2026-02-21T14:25:11.873Z"
    }
  },
  {
    "_id": {
      "$oid": "a4f38bdbe60b11d3640ee3e4"
    },
    "type": "challenge_status_update",
    "fkId": {
      "$oid": "e26b1f8bae84e20f70427f41"
    },
    "userId": {
      "$oid": "2bc621e1361d668aaabfbf57"
    },
    "isSeen": true,
    "createdAt": {
      "$date": "2026-02-21T14:24:22.384Z"
    }
  },
  {
    "_id": {
      "$oid": "cf915324b2952582117b6052"
    },
    "type": "idea_upvoted",
    "fkId": {
      "$oid": "34a85eb889536ac0af987ed7"
    },
    "userId": {
      "$oid": "206e353ed387b5a732cb1f0e"
    },
    "isSeen": false,
    "createdAt": {
      "$date": "2026-02-21T14:28:26.391Z"
    }
  },
  {
    "_id": {
      "$oid": "7057dd5e4b077a15a9cba87f"
    },
    "type": "challenge_upvoted",
    "fkId": {
      "$oid": "9b1ee63a06c2683ac9bfa411"
    },
    "userId": {
      "$oid": "18453cdfc20c9d7e345da6bb"
    },
    "isSeen": true,
    "createdAt": {
      "$date": "2026-02-21T14:37:35.646Z"
    }
  },
  {
    "_id": {
      "$oid": "097dc4511c4a48ac5bf5e185"
    },
    "type": "idea_deleted",
    "fkId": {
      "$oid": "819c2c2886d5df137793e83b"
    },
    "userId": {
      "$oid": "d6d689a4cf42160b67a413c6"
    },
    "isSeen": false,
    "createdAt": {
      "$date": "2026-02-21T14:23:45.235Z"
    }
  },
  {
    "_id": {
      "$oid": "0505cc6686670c5642f01148"
    },
    "type": "idea_subscribed",
    "fkId": {
      "$oid": "48de8c39447ab4717d6b60ca"
    },
    "userId": {
      "$oid": "ec3672e7f3cb324cb2c22642"
    },
    "isSeen": false,
    "createdAt": {
      "$date": "2026-02-21T14:39:04.700Z"
    }
  },
  {
    "_id": {
      "$oid": "0c8a02548134bca948ddd07d"
    },
    "type": "idea_edited",
    "fkId": {
      "$oid": "4b89ae040c8efecc4b2702ca"
    },
    "userId": {
      "$oid": "ec3672e7f3cb324cb2c22642"
    },
    "isSeen": true,
    "createdAt": {
      "$date": "2026-02-21T14:34:24.502Z"
    }
  },
  {
    "_id": {
      "$oid": "2b31da52748274a337289a93"
    },
    "type": "challenge_edited",
    "fkId": {
      "$oid": "5c0afe02805d5fc63f0ba68c"
    },
    "userId": {
      "$oid": "308297a4c754ce1f5200ce85"
    },
    "isSeen": false,
    "createdAt": {
      "$date": "2026-02-21T14:24:02.270Z"
    }
  },
  {
    "_id": {
      "$oid": "1d1982c08bc55806a2e7657a"
    },
    "type": "challenge_upvoted",
    "fkId": {
      "$oid": "ae2a841be8b323cae419de98"
    },
    "userId": {
      "$oid": "bef7a718d953662eebedbc13"
    },
    "isSeen": false,
    "createdAt": {
      "$date": "2026-02-21T14:33:20.438Z"
    }
  },
  {
    "_id": {
      "$oid": "654b505931a2f19937c1f869"
    },
    "type": "idea_commented",
    "fkId": {
      "$oid": "886e0024b1ebc7bfcfd81f22"
    },
    "userId": {
      "$oid": "68f7f79898ea61b7752b68c3"
    },
    "isSeen": true,
    "createdAt": {
      "$date": "2026-02-21T14:32:00.007Z"
    }
  },
  {
    "_id": {
      "$oid": "38921d40893b045f09a583ed"
    },
    "type": "idea_deleted",
    "fkId": {
      "$oid": "7a8cfbb8a7f1908549302d75"
    },
    "userId": {
      "$oid": "bacbb385c81efaae3612dfe0"
    },
    "isSeen": false,
    "createdAt": {
      "$date": "2026-02-21T14:28:17.723Z"
    }
  },
  {
    "_id": {
      "$oid": "23b2707acd5b62dca4759646"
    },
    "type": "idea_upvoted",
    "fkId": {
      "$oid": "afb64587094b9ff1c0a8dc27"
    },
    "userId": {
      "$oid": "b67695827cecb99d4ead1707"
    },
    "isSeen": false,
    "createdAt": {
      "$date": "2026-02-21T14:24:23.396Z"
    }
  },
  {
    "_id": {
      "$oid": "3f22e77a5b7ea301f71df49f"
    },
    "type": "idea_subscribed",
    "fkId": {
      "$oid": "afb64587094b9ff1c0a8dc27"
    },
    "userId": {
      "$oid": "f546ff3e8b00451f67c3724d"
    },
    "isSeen": false,
    "createdAt": {
      "$date": "2026-02-21T14:35:45.097Z"
    }
  },
  {
    "_id": {
      "$oid": "08a5efc25fa9bbd2a8c22885"
    },
    "type": "challenge_edited",
    "fkId": {
      "$oid": "894fd748050ec8a7d6df11cb"
    },
    "userId": {
      "$oid": "268b8a5741b7bd1797a14026"
    },
    "isSeen": false,
    "createdAt": {
      "$date": "2026-02-21T14:29:47.868Z"
    }
  },
  {
    "_id": {
      "$oid": "49516712069cc58928553411"
    },
    "type": "idea_subscribed",
    "fkId": {
      "$oid": "111936514c1279d1f415f119"
    },
    "userId": {
      "$oid": "404f08da5d4fd716ff80b1e4"
    },
    "isSeen": false,
    "createdAt": {
      "$date": "2026-02-21T14:34:45.768Z"
    }
  },
  {
    "_id": {
      "$oid": "7517ae54e0a84facae4d0fd5"
    },
    "type": "challenge_status_update",
    "fkId": {
      "$oid": "05a72d8d66451cec8e8664f5"
    },
    "userId": {
      "$oid": "7266fc2a6ba991e5e9f1a626"
    },
    "isSeen": false,
    "createdAt": {
      "$date": "2026-02-21T14:24:20.075Z"
    }
  },
  {
    "_id": {
      "$oid": "35f9ea41d561f74b4bf171ab"
    },
    "type": "challenge_status_update",
    "fkId": {
      "$oid": "899a8351fd8627cd958ffc8e"
    },
    "userId": {
      "$oid": "268b8a5741b7bd1797a14026"
    },
    "isSeen": false,
    "createdAt": {
      "$date": "2026-02-21T14:38:46.895Z"
    }
  },
  {
    "_id": {
      "$oid": "a818ac0f2718560313ed5369"
    },
    "type": "challenge_deleted",
    "fkId": {
      "$oid": "682f67cfbe6aeb0a319a8253"
    },
    "userId": {
      "$oid": "2245086b5bc06d315ccedbdc"
    },
    "isSeen": false,
    "createdAt": {
      "$date": "2026-02-21T14:28:52.695Z"
    }
  },
  {
    "_id": {
      "$oid": "cb269f5f0c3087ca7d78eb05"
    },
    "type": "idea_edited",
    "fkId": {
      "$oid": "a2bb783fd06680321e007e43"
    },
    "userId": {
      "$oid": "2e69c5f1d36087afbd354bca"
    },
    "isSeen": false,
    "createdAt": {
      "$date": "2026-02-21T14:34:34.595Z"
    }
  },
  {
    "_id": {
      "$oid": "89173e2915833c84cce738a3"
    },
    "type": "idea_subscribed",
    "fkId": {
      "$oid": "87d5c3f31fae26580fc6c2f7"
    },
    "userId": {
      "$oid": "bef7a718d953662eebedbc13"
    },
    "isSeen": true,
    "createdAt": {
      "$date": "2026-02-21T14:30:01.454Z"
    }
  },
  {
    "_id": {
      "$oid": "294c24d22b3b7223f32860fb"
    },
    "type": "idea_commented",
    "fkId": {
      "$oid": "48de8c39447ab4717d6b60ca"
    },
    "userId": {
      "$oid": "268b8a5741b7bd1797a14026"
    },
    "isSeen": false,
    "createdAt": {
      "$date": "2026-02-21T14:38:12.849Z"
    }
  },
  {
    "_id": {
      "$oid": "88c908c86b7ea9b2d12b43c5"
    },
    "type": "challenge_upvoted",
    "fkId": {
      "$oid": "d1213f342b69b6d50f7f0990"
    },
    "userId": {
      "$oid": "679408078edc8d77ffd426b2"
    },
    "isSeen": false,
    "createdAt": {
      "$date": "2026-02-21T14:36:20.517Z"
    }
  },
  {
    "_id": {
      "$oid": "1b7b5e2b61bf3e83920ddc9d"
    },
    "type": "idea_deleted",
    "fkId": {
      "$oid": "8d78a2e96e74fc43fbe97a07"
    },
    "userId": {
      "$oid": "2bc621e1361d668aaabfbf57"
    },
    "isSeen": true,
    "createdAt": {
      "$date": "2026-02-21T14:39:22.717Z"
    }
  },
  {
    "_id": {
      "$oid": "a6ab15e36d54f388fbaa4dc9"
    },
    "type": "idea_deleted",
    "fkId": {
      "$oid": "899a8351fd8627cd958ffc8e"
    },
    "userId": {
      "$oid": "f546ff3e8b00451f67c3724d"
    },
    "isSeen": true,
    "createdAt": {
      "$date": "2026-02-21T14:29:59.865Z"
    }
  }
]